{"inkVersion":20,"root":[["\n","ev",{"VAR?":"chief_quest_finished"},"/ev",[{"->":".^.b","c":true},{"b":["^ ",{"->":"finishQuest"},{"->":"0.5"},null]}],"nop","\n","ev",{"VAR?":"chief_first"},"/ev",[{"->":".^.b","c":true},{"b":["^ ",{"->":"main"},{"->":"0.12"},null]}],[{"->":".^.b"},{"b":["^ ",{"->":"comebackAccepted"},{"->":"0.12"},null]}],"nop","\n",["done",{"#f":5,"#n":"g-0"}],null],"done",{"main":[["ev",false,"/ev",{"VAR=":"chief_first","re":true},"^Qabil, be careful with that thing... Oh Nim, good you're here! ",{"#":"speaker:Chief Turum"},{"#":"portrait:mentor"},{"#":"layout:right"},"\n","^Do you need my help? ",{"#":"speaker:Nim"},{"#":"portrait:mentor"},{"#":"layout:left"},"\n","^Yes, we need to clear up a place where we can stay the night. ",{"#":"speaker:Chief Turum"},{"#":"portrait:mentor"},{"#":"layout:right"},"\n","^Can you scout further ahead and see if you can find a suitable place to set up the camp? ",{"#":"speaker:Chief Turum"},{"#":"portrait:mentor"},{"#":"layout:right"},"\n","ev","str","^Yes","/str","/ev",{"*":".^.c-0","flg":20},"ev","str","^No","/str","/ev",{"*":".^.c-1","flg":20},{"c-0":["\n","^Ofcourse I can! ",{"#":"speaker:Nim"},{"#":"portrait:mentor"},{"#":"layout:left"},"\n","ev",true,"/ev",{"VAR=":"chief_accept","re":true},"^Good! Please hurry, the storm is starting to pick up speed. ",{"#":"speaker:Chief Turum"},{"#":"portrait:mentor"},{"#":"layout:right"},"\n","end",{"#f":5}],"c-1":["\n","^Can't you ask Habil or Qabil? ",{"#":"speaker:Nim"},{"#":"portrait:mentor"},{"#":"layout:left"},"\n","ev",true,"/ev",{"VAR=":"chief_accept","re":true},"^Those two have other chores that they must do right now. Talk to me again when a camp site is cleared. ",{"#":"speaker:Chief Turum"},{"#":"portrait:mentor"},{"#":"layout:right"},"\n","end",{"#f":5}]}],{"#f":1}],"comebackAccepted":["^Nim, we don't have all the time in the world. ",{"#":"speaker:Chief Turum"},{"#":"portrait:mentor"},{"#":"layout:right"},"\n","^We can't place out our tents if the area is not secure. ",{"#":"speaker:Chief Turum"},{"#":"portrait:mentor"},{"#":"layout:right"},"\n","end",{"#f":1}],"finishQuest":["^Great work! Now if you will excuse me... ",{"#":"speaker:Chief Turum"},{"#":"portrait:mentor"},{"#":"layout:right"},"\n","^All right people, let's move it! ",{"#":"speaker:Chief Turum"},{"#":"portrait:mentor"},{"#":"layout:right"},"\n","end",{"#f":1}],"global decl":["ev",true,{"VAR=":"first_dialogue"},true,{"VAR=":"chief_first"},false,{"VAR=":"chief_accept"},false,{"VAR=":"chief_quest_finished"},true,{"VAR=":"bolani_first"},false,{"VAR=":"bolani_accept"},false,{"VAR=":"bolani_quest_finished"},true,{"VAR=":"qabil_first"},false,{"VAR=":"qabil_accept"},false,{"VAR=":"qabil_quest_finished"},false,{"VAR=":"finished_quest_clear_rubble"},false,{"VAR=":"Tutorial_EndSection"},true,{"VAR=":"MQ2C_Oasis_Kulan_first"},false,{"VAR=":"MQ2C_Oasis_Kulan_accept"},false,{"VAR=":"MQ2C_Oasis_Kulan_quest_finished"},true,{"VAR=":"MQ2B_Oasis_Qabil_first"},false,{"VAR=":"MQ2B_Oasis_Qabil_accept"},false,{"VAR=":"MQ2B_Oasis_Qabil_quest_finished"},true,{"VAR=":"MQ1_FireTemple_Nari_first"},true,{"VAR=":"MQ1_FireTemple_Nari_NotComplete"},"/ev","end",null],"#f":1}],"listDefs":{}}